[
  {
    "Id": 1,
    "Nome": "Fabio",
    "Sobrenome": "Silva",
    "Telefone": "11996394655",
    "Ra": 1
  },
  {
    "Id": 2,
    "Nome": "Evelini",
    "Sobrenome": "Silva",
    "Telefone": "11996394645",
    "Ra": 1
  },
  {
    "Id": 3,
    "Nome": "Helena",
    "Sobrenome": "Silva",
    "Telefone": "11996394635",
    "Ra": 1
  },
  {
    "Id": 4,
    "Nome": "Próximo",
    "Sobrenome": "Silva",
    "Telefone": "11996394625",
    "Ra": 1
  },
  {
    "Id": 5,
    "Nome": "Quinto registro",
    "Sobrenome": "aaaaa",
    "Telefone": "11996394625",
    "Ra": 1
  },
  {
    "Id": 6,
    "Nome": "Next alterado 2",
    "Sobrenome": "Next alterado2",
    "Telefone": "11996394655",
    "Ra": 1
  },
  {
    "Id": 7,
    "Nome": "mais um",
    "Sobrenome": "mais um",
    "Telefone": "mais um",
    "Ra": 8
  },
  {
    "Id": 8,
    "Nome": "mais",
    "Sobrenome": "dois",
    "Telefone": "dois",
    "Ra": 9
  },
  {
    "Id": 9,
    "Nome": "fabio",
    "Sobrenome": "aaaaab",
    "Telefone": "bbbb",
    "Ra": 10
  },
  {
    "Id": 10,
    "Nome": "aaaa",
    "Sobrenome": "bbbb",
    "Telefone": "ccccc",
    "Ra": 0
  },
  {
    "Id": 11,
    "Nome": "1",
    "Sobrenome": "2",
    "Telefone": "3",
    "Ra": 5
  }
]